concurrentpandas.py
ConcurrentPandas-0.1.2.data/scripts/benchmark.py
ConcurrentPandas-0.1.2.data/scripts/README.md
ConcurrentPandas-0.1.2.data/scripts/AUTHORS.rst
ConcurrentPandas-0.1.2.data/scripts/concurrentpandas.py
ConcurrentPandas-0.1.2.data/scripts/LICENSE
ConcurrentPandas-0.1.2.dist-info/pbr.json
ConcurrentPandas-0.1.2.dist-info/WHEEL
ConcurrentPandas-0.1.2.dist-info/DESCRIPTION.rst
ConcurrentPandas-0.1.2.dist-info/metadata.json
ConcurrentPandas-0.1.2.dist-info/top_level.txt
ConcurrentPandas-0.1.2.dist-info/RECORD
ConcurrentPandas-0.1.2.dist-info/METADATA
