Metadata-Version: 2.0
Name: ConcurrentPandas
Version: 0.1.2
Summary: Download data using pandas with multi-threading and multi-processing.
Home-page: https://github.com/briwilcox/Concurrent-Pandas
Author: Brian Wilcox
Author-email: UNKNOWN
License: Apache Software License
Keywords: Panda,Pandas,DataFrame,Data Frame,Analysis,
Platform: UNKNOWN
Classifier: Development Status :: 2 - Pre-Alpha
Classifier: Intended Audience :: Developers
Classifier: Intended Audience :: Science/Research
Classifier: Intended Audience :: Education
Classifier: Intended Audience :: Financial and Insurance Industry
Classifier: Natural Language :: English
Classifier: License :: OSI Approved :: Apache Software License
Classifier: Operating System :: OS Independent
Classifier: Programming Language :: Python
Classifier: Programming Language :: Python :: 2
Classifier: Programming Language :: Python :: 2.7
Classifier: Programming Language :: Python :: 3
Classifier: Programming Language :: Python :: 3.3
Classifier: Programming Language :: Python :: 3.4
Classifier: Topic :: Software Development :: Libraries :: Python Modules
Classifier: Topic :: Scientific/Engineering
Classifier: Topic :: Scientific/Engineering :: Bio-Informatics
Classifier: Topic :: Scientific/Engineering :: Information Analysis
Requires-Dist: Quandl
Requires-Dist: pandas (>=0.16.0)
Requires-Dist: BeautifulSoup4
